argparse_boost/__init__.py
argparse_boost/_argument_parser.py
argparse_boost/_config.py
argparse_boost/_discovery.py
argparse_boost/_exceptions.py
argparse_boost/_framework.py
argparse_boost/_parsers.py
argparse_boost/py.typed
argparse_boost-0.2.0.dist-info/licenses/LICENSE
argparse_boost-0.2.0.dist-info/METADATA
argparse_boost-0.2.0.dist-info/WHEEL
argparse_boost-0.2.0.dist-info/top_level.txt
argparse_boost-0.2.0.dist-info/zip-safe
argparse_boost-0.2.0.dist-info/RECORD
