Metadata-Version: 2.4
Name: argparse-boost
Version: 0.2.0
Summary: Extension module for argparse
Author: yakimka
License: MIT
Project-URL: repository, https://github.com/yakimka/argparse-boost
Platform: Linux
Classifier: Development Status :: 3 - Alpha
Classifier: Intended Audience :: Developers
Classifier: Operating System :: OS Independent
Classifier: Topic :: Software Development :: Libraries :: Python Modules
Classifier: License :: OSI Approved :: MIT License
Classifier: Programming Language :: Python :: 3
Classifier: Programming Language :: Python :: 3.10
Classifier: Programming Language :: Python :: 3.11
Classifier: Programming Language :: Python :: 3.12
Classifier: Programming Language :: Python :: 3.13
Classifier: Programming Language :: Python :: 3.14
Classifier: Programming Language :: Python :: Implementation :: PyPy
Requires-Python: <4.0.0,>=3.10
License-File: LICENSE
Dynamic: license-file
